git_commit_manager/__init__.py
git_commit_manager/__main__.py
git_commit_manager/helper.py
git_commit_manager/command/__init__.py
git_commit_manager/command/commit.py
git_commit_manager/command/dump.py
git_commit_manager/command/init.py
git_commit_manager/command/migrate.py
git_commit_manager/command/next.py
git_commit_manager-1.0.dist-info/COPYING
git_commit_manager-1.0.dist-info/METADATA
git_commit_manager-1.0.dist-info/WHEEL
git_commit_manager-1.0.dist-info/entry_points.txt
git_commit_manager-1.0.dist-info/top_level.txt
git_commit_manager-1.0.dist-info/RECORD
